{
    "schemes": [
        "http"
    ],
    "swagger": "2.0",
    "info": {
        "description": "This is a book shop server.",
        "title": "Book Shop API",
        "termsOfService": "http://swagger.io/terms/",
        "contact": {
            "name": "API Support",
            "email": "your-email@domain.com"
        },
        "license": {
            "name": "Apache 2.0",
            "url": "http://www.apache.org/licenses/LICENSE-2.0.html"
        },
        "version": "1.0"
    },
    "host": "localhost:8080",
    "basePath": "/",
    "paths": {
        "/book": {
            "get": {
                "description": "Get a list of all available books, optionally filtered by category IDs",
                "consumes": [
                    "application/json"
                ],
                "produces": [
                    "application/json"
                ],
                "tags": [
                    "books"
                ],
                "summary": "Get available books",
                "parameters": [
                    {
                        "type": "array",
                        "items": {
                            "type": "integer"
                        },
                        "collectionFormat": "csv",
                        "description": "Category IDs to filter by",
                        "name": "categoryId",
                        "in": "query"
                    }
                ],
                "responses": {
                    "200": {
                        "description": "OK",
                        "schema": {
                            "type": "array",
                            "items": {
                                "$ref": "#/definitions/model.BookResponse"
                            }
                        }
                    },
                    "400": {
                        "description": "Bad Request",
                        "schema": {
                            "type": "string"
                        }
                    },
                    "500": {
                        "description": "Internal Server Error",
                        "schema": {
                            "type": "string"
                        }
                    }
                }
            },
            "post": {
                "security": [
                    {
                        "ApiKeyAuth": []
                    }
                ],
                "description": "Create a new book with the provided details",
                "consumes": [
                    "application/json"
                ],
                "produces": [
                    "application/json"
                ],
                "tags": [
                    "books"
                ],
                "summary": "Create a new book",
                "parameters": [
                    {
                        "description": "Book details",
                        "name": "book",
                        "in": "body",
                        "required": true,
                        "schema": {
                            "$ref": "#/definitions/model.BookRequest"
                        }
                    }
                ],
                "responses": {
                    "201": {
                        "description": "Created",
                        "schema": {
                            "$ref": "#/definitions/model.BookResponse"
                        }
                    },
                    "400": {
                        "description": "Bad Request",
                        "schema": {
                            "type": "string"
                        }
                    },
                    "401": {
                        "description": "Unauthorized",
                        "schema": {
                            "type": "string"
                        }
                    },
                    "500": {
                        "description": "Internal Server Error",
                        "schema": {
                            "type": "string"
                        }
                    }
                }
            }
        },
        "/book/{id}": {
            "get": {
                "description": "Get a book's details by its ID",
                "consumes": [
                    "application/json"
                ],
                "produces": [
                    "application/json"
                ],
                "tags": [
                    "books"
                ],
                "summary": "Get book by ID",
                "parameters": [
                    {
                        "type": "integer",
                        "description": "Book ID",
                        "name": "id",
                        "in": "path",
                        "required": true
                    }
                ],
                "responses": {
                    "200": {
                        "description": "OK",
                        "schema": {
                            "$ref": "#/definitions/model.BookResponse"
                        }
                    },
                    "400": {
                        "description": "Bad Request",
                        "schema": {
                            "type": "string"
                        }
                    },
                    "404": {
                        "description": "Not Found",
                        "schema": {
                            "type": "string"
                        }
                    },
                    "500": {
                        "description": "Internal Server Error",
                        "schema": {
                            "type": "string"
                        }
                    }
                }
            },
            "put": {
                "security": [
                    {
                        "ApiKeyAuth": []
                    }
                ],
                "description": "Update an existing book's details",
                "consumes": [
                    "application/json"
                ],
                "produces": [
                    "application/json"
                ],
                "tags": [
                    "books"
                ],
                "summary": "Update a book",
                "parameters": [
                    {
                        "type": "integer",
                        "description": "Book ID",
                        "name": "id",
                        "in": "path",
                        "required": true
                    },
                    {
                        "description": "Updated book details",
                        "name": "book",
                        "in": "body",
                        "required": true,
                        "schema": {
                            "$ref": "#/definitions/model.BookRequest"
                        }
                    }
                ],
                "responses": {
                    "200": {
                        "description": "OK",
                        "schema": {
                            "$ref": "#/definitions/model.BookResponse"
                        }
                    },
                    "400": {
                        "description": "Bad Request",
                        "schema": {
                            "type": "string"
                        }
                    },
                    "401": {
                        "description": "Unauthorized",
                        "schema": {
                            "type": "string"
                        }
                    },
                    "404": {
                        "description": "Not Found",
                        "schema": {
                            "type": "string"
                        }
                    },
                    "500": {
                        "description": "Internal Server Error",
                        "schema": {
                            "type": "string"
                        }
                    }
                }
            },
            "delete": {
                "security": [
                    {
                        "ApiKeyAuth": []
                    }
                ],
                "description": "Delete a book by its ID",
                "consumes": [
                    "application/json"
                ],
                "produces": [
                    "application/json"
                ],
                "tags": [
                    "books"
                ],
                "summary": "Delete a book",
                "parameters": [
                    {
                        "type": "integer",
                        "description": "Book ID",
                        "name": "id",
                        "in": "path",
                        "required": true
                    }
                ],
                "responses": {
                    "200": {
                        "description": "OK",
                        "schema": {
                            "type": "string"
                        }
                    },
                    "400": {
                        "description": "Bad Request",
                        "schema": {
                            "type": "string"
                        }
                    },
                    "401": {
                        "description": "Unauthorized",
                        "schema": {
                            "type": "string"
                        }
                    },
                    "404": {
                        "description": "Not Found",
                        "schema": {
                            "type": "string"
                        }
                    },
                    "500": {
                        "description": "Internal Server Error",
                        "schema": {
                            "type": "string"
                        }
                    }
                }
            }
        },
        "/cart": {
            "get": {
                "security": [
                    {
                        "ApiKeyAuth": []
                    }
                ],
                "description": "Get the current user's shopping cart contents",
                "consumes": [
                    "application/json"
                ],
                "produces": [
                    "application/json"
                ],
                "tags": [
                    "cart"
                ],
                "summary": "Get user's cart",
                "responses": {
                    "200": {
                        "description": "OK",
                        "schema": {
                            "type": "array",
                            "items": {
                                "$ref": "#/definitions/model.BookResponse"
                            }
                        }
                    },
                    "400": {
                        "description": "Bad Request",
                        "schema": {
                            "type": "string"
                        }
                    },
                    "401": {
                        "description": "Unauthorized",
                        "schema": {
                            "type": "string"
                        }
                    },
                    "500": {
                        "description": "Internal Server Error",
                        "schema": {
                            "type": "string"
                        }
                    }
                }
            }
        },
        "/cart/add": {
            "post": {
                "security": [
                    {
                        "ApiKeyAuth": []
                    }
                ],
                "description": "Add a book to the current user's shopping cart",
                "consumes": [
                    "application/json"
                ],
                "produces": [
                    "application/json"
                ],
                "tags": [
                    "cart"
                ],
                "summary": "Add book to cart",
                "parameters": [
                    {
                        "description": "Book to add to cart",
                        "name": "request",
                        "in": "body",
                        "required": true,
                        "schema": {
                            "$ref": "#/definitions/model.AddToCartRequest"
                        }
                    }
                ],
                "responses": {
                    "202": {
                        "description": "Accepted",
                        "schema": {
                            "type": "string"
                        }
                    },
                    "400": {
                        "description": "Bad Request",
                        "schema": {
                            "type": "string"
                        }
                    },
                    "401": {
                        "description": "Unauthorized",
                        "schema": {
                            "type": "string"
                        }
                    },
                    "404": {
                        "description": "Book not found",
                        "schema": {
                            "type": "string"
                        }
                    },
                    "500": {
                        "description": "Internal Server Error",
                        "schema": {
                            "type": "string"
                        }
                    }
                }
            }
        },
        "/cart/purchase": {
            "post": {
                "security": [
                    {
                        "ApiKeyAuth": []
                    }
                ],
                "description": "Purchase all books in the current user's shopping cart",
                "consumes": [
                    "application/json"
                ],
                "produces": [
                    "application/json"
                ],
                "tags": [
                    "cart"
                ],
                "summary": "Purchase cart",
                "responses": {
                    "202": {
                        "description": "Accepted",
                        "schema": {
                            "type": "string"
                        }
                    },
                    "400": {
                        "description": "Bad Request",
                        "schema": {
                            "type": "string"
                        }
                    },
                    "401": {
                        "description": "Unauthorized",
                        "schema": {
                            "type": "string"
                        }
                    },
                    "422": {
                        "description": "Insufficient stock",
                        "schema": {
                            "type": "string"
                        }
                    },
                    "500": {
                        "description": "Internal Server Error",
                        "schema": {
                            "type": "string"
                        }
                    }
                }
            }
        },
        "/cart/remove": {
            "post": {
                "security": [
                    {
                        "ApiKeyAuth": []
                    }
                ],
                "description": "Remove a book from the current user's shopping cart",
                "consumes": [
                    "application/json"
                ],
                "produces": [
                    "application/json"
                ],
                "tags": [
                    "cart"
                ],
                "summary": "Remove book from cart",
                "parameters": [
                    {
                        "description": "Book to remove from cart",
                        "name": "request",
                        "in": "body",
                        "required": true,
                        "schema": {
                            "$ref": "#/definitions/model.AddToCartRequest"
                        }
                    }
                ],
                "responses": {
                    "202": {
                        "description": "Accepted",
                        "schema": {
                            "type": "string"
                        }
                    },
                    "400": {
                        "description": "Bad Request",
                        "schema": {
                            "type": "string"
                        }
                    },
                    "401": {
                        "description": "Unauthorized",
                        "schema": {
                            "type": "string"
                        }
                    },
                    "404": {
                        "description": "Book not found in cart",
                        "schema": {
                            "type": "string"
                        }
                    },
                    "500": {
                        "description": "Internal Server Error",
                        "schema": {
                            "type": "string"
                        }
                    }
                }
            }
        },
        "/category": {
            "get": {
                "description": "Get a list of all available categories",
                "consumes": [
                    "application/json"
                ],
                "produces": [
                    "application/json"
                ],
                "tags": [
                    "categories"
                ],
                "summary": "Get all categories",
                "responses": {
                    "200": {
                        "description": "OK",
                        "schema": {
                            "type": "array",
                            "items": {
                                "$ref": "#/definitions/model.Category"
                            }
                        }
                    },
                    "500": {
                        "description": "Internal Server Error",
                        "schema": {
                            "type": "string"
                        }
                    }
                }
            },
            "put": {
                "security": [
                    {
                        "ApiKeyAuth": []
                    }
                ],
                "description": "Update an existing category's details",
                "consumes": [
                    "application/json"
                ],
                "produces": [
                    "application/json"
                ],
                "tags": [
                    "categories"
                ],
                "summary": "Update a category",
                "parameters": [
                    {
                        "description": "Updated category details",
                        "name": "category",
                        "in": "body",
                        "required": true,
                        "schema": {
                            "$ref": "#/definitions/model.Category"
                        }
                    }
                ],
                "responses": {
                    "200": {
                        "description": "OK",
                        "schema": {
                            "$ref": "#/definitions/model.Category"
                        }
                    },
                    "400": {
                        "description": "Bad Request",
                        "schema": {
                            "type": "string"
                        }
                    },
                    "401": {
                        "description": "Unauthorized",
                        "schema": {
                            "type": "string"
                        }
                    },
                    "404": {
                        "description": "Not Found",
                        "schema": {
                            "type": "string"
                        }
                    },
                    "500": {
                        "description": "Internal Server Error",
                        "schema": {
                            "type": "string"
                        }
                    }
                }
            },
            "post": {
                "security": [
                    {
                        "ApiKeyAuth": []
                    }
                ],
                "description": "Create a new category with the provided details",
                "consumes": [
                    "application/json"
                ],
                "produces": [
                    "application/json"
                ],
                "tags": [
                    "categories"
                ],
                "summary": "Create a new category",
                "parameters": [
                    {
                        "description": "Category details",
                        "name": "category",
                        "in": "body",
                        "required": true,
                        "schema": {
                            "$ref": "#/definitions/model.Category"
                        }
                    }
                ],
                "responses": {
                    "201": {
                        "description": "Created",
                        "schema": {
                            "$ref": "#/definitions/model.Category"
                        }
                    },
                    "400": {
                        "description": "Bad Request",
                        "schema": {
                            "type": "string"
                        }
                    },
                    "401": {
                        "description": "Unauthorized",
                        "schema": {
                            "type": "string"
                        }
                    },
                    "500": {
                        "description": "Internal Server Error",
                        "schema": {
                            "type": "string"
                        }
                    }
                }
            }
        },
        "/category/{id}": {
            "get": {
                "description": "Get a category's details by its ID",
                "consumes": [
                    "application/json"
                ],
                "produces": [
                    "application/json"
                ],
                "tags": [
                    "categories"
                ],
                "summary": "Get category by ID",
                "parameters": [
                    {
                        "type": "integer",
                        "description": "Category ID",
                        "name": "id",
                        "in": "path",
                        "required": true
                    }
                ],
                "responses": {
                    "200": {
                        "description": "OK",
                        "schema": {
                            "$ref": "#/definitions/model.Category"
                        }
                    },
                    "400": {
                        "description": "Bad Request",
                        "schema": {
                            "type": "string"
                        }
                    },
                    "404": {
                        "description": "Not Found",
                        "schema": {
                            "type": "string"
                        }
                    },
                    "500": {
                        "description": "Internal Server Error",
                        "schema": {
                            "type": "string"
                        }
                    }
                }
            },
            "delete": {
                "security": [
                    {
                        "ApiKeyAuth": []
                    }
                ],
                "description": "Delete a category by its ID",
                "consumes": [
                    "application/json"
                ],
                "produces": [
                    "application/json"
                ],
                "tags": [
                    "categories"
                ],
                "summary": "Delete a category",
                "parameters": [
                    {
                        "type": "integer",
                        "description": "Category ID",
                        "name": "id",
                        "in": "path",
                        "required": true
                    }
                ],
                "responses": {
                    "200": {
                        "description": "OK",
                        "schema": {
                            "type": "string"
                        }
                    },
                    "400": {
                        "description": "Bad Request",
                        "schema": {
                            "type": "string"
                        }
                    },
                    "401": {
                        "description": "Unauthorized",
                        "schema": {
                            "type": "string"
                        }
                    },
                    "404": {
                        "description": "Not Found",
                        "schema": {
                            "type": "string"
                        }
                    },
                    "500": {
                        "description": "Internal Server Error",
                        "schema": {
                            "type": "string"
                        }
                    }
                }
            }
        },
        "/login": {
            "post": {
                "description": "Authenticate user and get JWT token",
                "consumes": [
                    "application/json"
                ],
                "produces": [
                    "application/json"
                ],
                "tags": [
                    "auth"
                ],
                "summary": "User login",
                "parameters": [
                    {
                        "description": "Login credentials",
                        "name": "request",
                        "in": "body",
                        "required": true,
                        "schema": {
                            "$ref": "#/definitions/model.UserRequest"
                        }
                    }
                ],
                "responses": {
                    "200": {
                        "description": "Returns JWT token",
                        "schema": {
                            "type": "object",
                            "additionalProperties": {
                                "type": "string"
                            }
                        }
                    },
                    "400": {
                        "description": "Bad Request",
                        "schema": {
                            "type": "string"
                        }
                    },
                    "401": {
                        "description": "Unauthorized",
                        "schema": {
                            "type": "string"
                        }
                    },
                    "500": {
                        "description": "Internal Server Error",
                        "schema": {
                            "type": "string"
                        }
                    }
                }
            }
        },
        "/register": {
            "post": {
                "description": "Register a new user account",
                "consumes": [
                    "application/json"
                ],
                "produces": [
                    "application/json"
                ],
                "tags": [
                    "auth"
                ],
                "summary": "Register new user",
                "parameters": [
                    {
                        "description": "Registration details",
                        "name": "request",
                        "in": "body",
                        "required": true,
                        "schema": {
                            "$ref": "#/definitions/model.UserRequest"
                        }
                    }
                ],
                "responses": {
                    "201": {
                        "description": "User created successfully",
                        "schema": {
                            "type": "object",
                            "additionalProperties": {
                                "type": "string"
                            }
                        }
                    },
                    "400": {
                        "description": "Bad Request",
                        "schema": {
                            "type": "string"
                        }
                    },
                    "409": {
                        "description": "Username already exists",
                        "schema": {
                            "type": "string"
                        }
                    },
                    "500": {
                        "description": "Internal Server Error",
                        "schema": {
                            "type": "string"
                        }
                    }
                }
            }
        }
    },
    "definitions": {
        "model.AddToCartRequest": {
            "type": "object",
            "properties": {
                "book_id": {
                    "type": "integer"
                }
            }
        },
        "model.BookRequest": {
            "type": "object",
            "properties": {
                "author": {
                    "type": "string"
                },
                "category_id": {
                    "type": "integer"
                },
                "price": {
                    "type": "integer"
                },
                "stock": {
                    "type": "integer"
                },
                "title": {
                    "type": "string"
                },
                "year": {
                    "type": "integer"
                }
            }
        },
        "model.BookResponse": {
            "type": "object",
            "properties": {
                "author": {
                    "type": "string"
                },
                "category_id": {
                    "type": "integer"
                },
                "price": {
                    "type": "integer"
                },
                "stock": {
                    "type": "integer"
                },
                "title": {
                    "type": "string"
                },
                "year": {
                    "type": "integer"
                }
            }
        },
        "model.Category": {
            "type": "object",
            "properties": {
                "name": {
                    "type": "string"
                }
            }
        },
        "model.UserRequest": {
            "type": "object",
            "properties": {
                "password": {
                    "type": "string"
                },
                "username": {
                    "type": "string"
                }
            }
        }
    }
}